beamme-0.1.4.dist-info/RECORD
beamme-0.1.4.dist-info/WHEEL
beamme-0.1.4.dist-info/top_level.txt
beamme-0.1.4.dist-info/METADATA
beamme-0.1.4.dist-info/licenses/LICENSE
beamme/version.py
beamme/__init__.py
beamme/four_c/input_file_dump_item.py
beamme/four_c/header_functions.py
beamme/four_c/material.py
beamme/four_c/element_volume.py
beamme/four_c/dbc_monitor.py
beamme/four_c/element_beam.py
beamme/four_c/solid_shell_thickness_direction.py
beamme/four_c/run_four_c.py
beamme/four_c/input_file_mappings.py
beamme/four_c/__init__.py
beamme/four_c/beam_interaction_conditions.py
beamme/four_c/model_importer.py
beamme/four_c/beam_potential.py
beamme/four_c/input_file.py
beamme/four_c/four_c_types.py
beamme/four_c/function_utility.py
beamme/four_c/locsys_condition.py
beamme/core/nurbs_patch.py
beamme/core/material.py
beamme/core/element_volume.py
beamme/core/element_beam.py
beamme/core/base_mesh_item.py
beamme/core/conf.py
beamme/core/boundary_condition.py
beamme/core/coupling.py
beamme/core/__init__.py
beamme/core/mesh.py
beamme/core/element.py
beamme/core/container.py
beamme/core/vtk_writer.py
beamme/core/geometry_set.py
beamme/core/node.py
beamme/core/rotation.py
beamme/core/mesh_utils.py
beamme/core/function.py
beamme/mesh_creation_functions/beam_splinepy.py
beamme/mesh_creation_functions/beam_parametric_curve.py
beamme/mesh_creation_functions/beam_arc.py
beamme/mesh_creation_functions/__init__.py
beamme/mesh_creation_functions/nurbs_geometries.py
beamme/mesh_creation_functions/nurbs_utils.py
beamme/mesh_creation_functions/beam_node_continuation.py
beamme/mesh_creation_functions/beam_generic.py
beamme/mesh_creation_functions/beam_line.py
beamme/mesh_creation_functions/nurbs_generic.py
beamme/mesh_creation_functions/beam_helix.py
beamme/mesh_creation_functions/applications/beam_honeycomb.py
beamme/mesh_creation_functions/applications/beam_wire.py
beamme/mesh_creation_functions/applications/__init__.py
beamme/mesh_creation_functions/applications/beam_stent.py
beamme/mesh_creation_functions/applications/beam_fibers_in_rectangle.py
beamme/utils/__init__.py
beamme/utils/environment.py
