Metadata-Version: 2.4
Name: BeamMe
Version: 0.1.4
Summary: BeamMe: A general purpose 3D beam finite element input generator
Author: BeamMe Authors
Maintainer-email: Ivo Steinbrecher <ivo.steinbrecher@unibw.de>, David Rudlstorfer <david.rudlstorfer@tum.de>
License: The MIT License (MIT)
Project-URL: Homepage, https://beamme-py.github.io/beamme/
Project-URL: Documentation, https://beamme-py.github.io/beamme/api-documentation/
Project-URL: Repository, https://github.com/beamme-py/beamme/
Project-URL: Issues, https://github.com/beamme-py/beamme/issues/
License-File: LICENSE
Requires-Dist: autograd
Requires-Dist: geomdl
Requires-Dist: ipykernel
Requires-Dist: notebook
Requires-Dist: numpy
Requires-Dist: numpy-quaternion
Requires-Dist: pyvista[jupyter]
Requires-Dist: scipy
Requires-Dist: splinepy
Requires-Dist: vedo==2024.5.2
Requires-Dist: vtk
Provides-Extra: cubitpy
Requires-Dist: cubitpy; extra == "cubitpy"
Provides-Extra: fourc
Requires-Dist: fourcipp; extra == "fourc"
Provides-Extra: dev
Requires-Dist: coverage-badge; extra == "dev"
Requires-Dist: coverage; extra == "dev"
Requires-Dist: pdoc; extra == "dev"
Requires-Dist: pre-commit; extra == "dev"
Requires-Dist: pytest; extra == "dev"
Requires-Dist: pytest-cov; extra == "dev"
Requires-Dist: testbook; extra == "dev"
Requires-Dist: vistools; extra == "dev"
Requires-Dist: xmltodict; extra == "dev"
Dynamic: license-file
